cliifs/IFS.py
cliifs/PlotWindow.py
cliifs/SignalHandler.py
cliifs/__init__.py
cliifs/cliifs.py
cliifs-0.61.dist-info/LICENSE
cliifs-0.61.dist-info/METADATA
cliifs-0.61.dist-info/WHEEL
cliifs-0.61.dist-info/entry_points.txt
cliifs-0.61.dist-info/top_level.txt
cliifs-0.61.dist-info/RECORD
