Metadata-Version: 2.1
Name: cliifs
Version: 0.61
Summary: Render and view fractals from iterated functions systems right on your terminal.
Home-page: https://github.com/raphaelreyna/cliifs
Author: Raphael Reyna
Author-email: raphaelreyna@protonmail.com
License: GPL-3.0
Project-URL: Bug Tracker, https://github.com/raphaelreyna/cliifs/issues
Project-URL: Documentation, https://github.com/raphaelreyna/cliifs
Project-URL: Source Code, https://github.com/raphaelreyna/cliifs/issues
Keywords: fractals chaos ifs
Platform: UNKNOWN
